sphericalunet/__init__.py
sphericalunet/layers.py
sphericalunet/model.py
sphericalunet/utils/__init__.py
sphericalunet/utils/create_reg_parameters.py
sphericalunet/utils/groupwise_reg.py
sphericalunet/utils/initial_rigid_align.py
sphericalunet/utils/interp_numpy.py
sphericalunet/utils/interp_torch.py
sphericalunet/utils/utils.py
sphericalunet/utils/vtk.py
sphericalunet/utils/neigh_indices/FScolortable.txt
sphericalunet/utils/neigh_indices/ROI_36_TO_NAMIC35.txt
sphericalunet/utils/neigh_indices/adj_mat_order_10242_rotated_0.mat
sphericalunet/utils/neigh_indices/adj_mat_order_10242_rotated_1.mat
sphericalunet/utils/neigh_indices/adj_mat_order_10242_rotated_2.mat
sphericalunet/utils/neigh_indices/adj_mat_order_12_rotated_0.mat
sphericalunet/utils/neigh_indices/adj_mat_order_12_rotated_1.mat
sphericalunet/utils/neigh_indices/adj_mat_order_12_rotated_2.mat
sphericalunet/utils/neigh_indices/adj_mat_order_162_rotated_0.mat
sphericalunet/utils/neigh_indices/adj_mat_order_162_rotated_1.mat
sphericalunet/utils/neigh_indices/adj_mat_order_162_rotated_2.mat
sphericalunet/utils/neigh_indices/adj_mat_order_163842_rotated_0.mat
sphericalunet/utils/neigh_indices/adj_mat_order_163842_rotated_1.mat
sphericalunet/utils/neigh_indices/adj_mat_order_163842_rotated_2.mat
sphericalunet/utils/neigh_indices/adj_mat_order_2562_rotated_0.mat
sphericalunet/utils/neigh_indices/adj_mat_order_2562_rotated_1.mat
sphericalunet/utils/neigh_indices/adj_mat_order_2562_rotated_2.mat
sphericalunet/utils/neigh_indices/adj_mat_order_40962_rotated_0.mat
sphericalunet/utils/neigh_indices/adj_mat_order_40962_rotated_1.mat
sphericalunet/utils/neigh_indices/adj_mat_order_40962_rotated_2.mat
sphericalunet/utils/neigh_indices/adj_mat_order_42_rotated_0.mat
sphericalunet/utils/neigh_indices/adj_mat_order_42_rotated_1.mat
sphericalunet/utils/neigh_indices/adj_mat_order_42_rotated_2.mat
sphericalunet/utils/neigh_indices/adj_mat_order_642_rotated_0.mat
sphericalunet-1.0.9.dist-info/LICENSE
sphericalunet-1.0.9.dist-info/METADATA
sphericalunet-1.0.9.dist-info/WHEEL
sphericalunet-1.0.9.dist-info/top_level.txt
sphericalunet-1.0.9.dist-info/RECORD
