Metadata-Version: 2.1
Name: sphericalunet
Version: 1.0.9
Summary: This is the tools for Spherical U-Net on spherical cortical surfaces
Home-page: https://github.com/zhaofenqiang/SphericalUNetPackage
Author: Fenqiang Zhao
Author-email: zhaofenqiang0221@gmail.com
License: UNKNOWN
Platform: UNKNOWN
Classifier: Programming Language :: Python :: 3
Classifier: License :: OSI Approved :: MIT License
Classifier: Operating System :: OS Independent
Requires-Python: >=3.6
Requires-Dist: numpy
Requires-Dist: scipy
